open_taranis/CLI.py
open_taranis/__init__.py
open_taranis/tools.py
open_taranis/web_front.py
open_taranis-0.1.7.dist-info/METADATA
open_taranis-0.1.7.dist-info/WHEEL
open_taranis-0.1.7.dist-info/entry_points.txt
open_taranis-0.1.7.dist-info/licenses/LICENSE
open_taranis-0.1.7.dist-info/RECORD
