Metadata-Version: 2.4
Name: open-taranis
Version: 0.1.7
Summary: Minimalist Python framework for AI agents logic-only coding with streaming, tool calls, and multi-LLM provider support
Author-email: SyntaxError4Life <lilian@zanomega.com>
License: GPL-3.0-or-later
License-File: LICENSE
Keywords: API,LLM
Classifier: License :: OSI Approved :: GNU General Public License v3 or later (GPLv3+)
Classifier: Programming Language :: Python :: 3
Requires-Python: >=3.8
Requires-Dist: bs4
Requires-Dist: openai
